{
  "peliculas": [
    {
      "nombre": "Pulp Fiction",
      "director": "Quentin Tarantino",
      "categoria": "Acción",
      "protagonistas": [
        "John Travolta",
        "  Samuel L. Jackson"
      ],
      "id": 0
    },
    {
      "nombre": "Titanic",
      "director": "James Cameron",
      "categoria": "Amor",
      "protagonistas": [
        "Leonardo Di Caprio",
        " Kate Winslet"
      ],
      "id": 1
    },
    {
      "nombre": "Prueba",
      "director": "Prueba",
      "categoria": "Terror",
      "protagonistas": [
        "Prueba"
      ],
      "id": 2
    }
  ]
}